Metadata-Version: 2.1
Name: pulumi-azure-justrun
Version: 0.2.1
Summary: Provides some simple components to run azure apps
Home-page: https://pulumi.com
License: Apache-2.0
Project-URL: Repository, https://github.com/pulumi/pulumi-azure-justrun
Platform: UNKNOWN
